jupyterlab_theme_melon/__init__.py
jupyterlab_theme_melon/_version.py
jupyterlab_theme_melon/labextension/build_log.json
jupyterlab_theme_melon/labextension/package.json
jupyterlab_theme_melon/labextension/static/lib_index_js.c3ff737a29f1894a5d1d.js
jupyterlab_theme_melon/labextension/static/lib_index_js.c3ff737a29f1894a5d1d.js.map
jupyterlab_theme_melon/labextension/static/remoteEntry.b00d7b737b3b1bf61df6.js
jupyterlab_theme_melon/labextension/static/remoteEntry.b00d7b737b3b1bf61df6.js.map
jupyterlab_theme_melon/labextension/static/style.js
jupyterlab_theme_melon/labextension/themes/jupyterlab_theme_melon/index.css
jupyterlab_theme_melon/labextension/themes/jupyterlab_theme_melon/index.js
jupyterlab_theme_melon-0.1.0.data/data/share/jupyter/labextensions/jupyterlab_theme_melon/build_log.json
jupyterlab_theme_melon-0.1.0.data/data/share/jupyter/labextensions/jupyterlab_theme_melon/package.json
jupyterlab_theme_melon-0.1.0.data/data/share/jupyter/labextensions/jupyterlab_theme_melon/static/lib_index_js.c3ff737a29f1894a5d1d.js
jupyterlab_theme_melon-0.1.0.data/data/share/jupyter/labextensions/jupyterlab_theme_melon/static/lib_index_js.c3ff737a29f1894a5d1d.js.map
jupyterlab_theme_melon-0.1.0.data/data/share/jupyter/labextensions/jupyterlab_theme_melon/static/remoteEntry.b00d7b737b3b1bf61df6.js
jupyterlab_theme_melon-0.1.0.data/data/share/jupyter/labextensions/jupyterlab_theme_melon/static/remoteEntry.b00d7b737b3b1bf61df6.js.map
jupyterlab_theme_melon-0.1.0.data/data/share/jupyter/labextensions/jupyterlab_theme_melon/static/style.js
jupyterlab_theme_melon-0.1.0.data/data/share/jupyter/labextensions/jupyterlab_theme_melon/themes/jupyterlab_theme_melon/index.css
jupyterlab_theme_melon-0.1.0.data/data/share/jupyter/labextensions/jupyterlab_theme_melon/themes/jupyterlab_theme_melon/index.js
jupyterlab_theme_melon-0.1.0.data/data/share/jupyter/labextensions/jupyterlab_theme_melon/install.json
jupyterlab_theme_melon-0.1.0.dist-info/METADATA
jupyterlab_theme_melon-0.1.0.dist-info/WHEEL
jupyterlab_theme_melon-0.1.0.dist-info/licenses/LICENSE
jupyterlab_theme_melon-0.1.0.dist-info/RECORD
