Metadata-Version: 2.4
Name: jupyterlab_theme_melon
Version: 0.1.0
Summary: a dark theme for jupyterlab
Project-URL: Homepage, https://github.com/ursulams/jupyterlab_theme_melon
Project-URL: Bug Tracker, https://github.com/ursulams/jupyterlab_theme_melon/issues
Project-URL: Repository, https://github.com/ursulams/jupyterlab_theme_melon
Author-email: ursulams <ursula.kaczmarek@gmail.com>
License: BSD 3-Clause License
License-File: LICENSE
Keywords: jupyter,jupyterlab,jupyterlab-extension
Classifier: Framework :: Jupyter
Classifier: Framework :: Jupyter :: JupyterLab
Classifier: Framework :: Jupyter :: JupyterLab :: 4
Classifier: Framework :: Jupyter :: JupyterLab :: Extensions
Classifier: Framework :: Jupyter :: JupyterLab :: Extensions :: Prebuilt
Classifier: Framework :: Jupyter :: JupyterLab :: Extensions :: Themes
Classifier: License :: OSI Approved :: BSD License
Classifier: Programming Language :: Python
Classifier: Programming Language :: Python :: 3
Classifier: Programming Language :: Python :: 3.10
Classifier: Programming Language :: Python :: 3.11
Classifier: Programming Language :: Python :: 3.12
Classifier: Programming Language :: Python :: 3.13
Classifier: Programming Language :: Python :: 3.14
Requires-Python: >=3.10
